superforecast/__init__.py
superforecast/client.py
superforecast-0.1.4.dist-info/LICENSE
superforecast-0.1.4.dist-info/METADATA
superforecast-0.1.4.dist-info/WHEEL
superforecast-0.1.4.dist-info/top_level.txt
superforecast-0.1.4.dist-info/RECORD
