Metadata-Version: 2.2
Name: superforecast
Version: 0.1.4
Summary: Super Forecast - A modern forecasting API client powered by bio-inspired AI models
Author: San Martim
Author-email: San Martim <superforecast@dataspoc.com>
License: MIT License
Keywords: forecast,forecasting,AI models,timeseries,demand forecasting,energy forecasting,financial market forecasting
Classifier: Development Status :: 5 - Production/Stable
Classifier: Intended Audience :: Developers
Classifier: Topic :: Scientific/Engineering :: Artificial Intelligence
Classifier: Programming Language :: Python :: 3
Classifier: License :: OSI Approved :: MIT License
License-File: LICENSE
Requires-Dist: requests
Dynamic: author
